proxy_messages_aiogram/__init__.py
proxy_messages_aiogram/metrics.py
proxy_messages_aiogram/permissions_managers.py
proxy_messages_aiogram/proxy_managers.py
proxy_messages_aiogram/storages/__init__.py
proxy_messages_aiogram/storages/base.py
proxy_messages_aiogram/storages/memory_storage.py
proxy_messages_aiogram/storages/redis_storage.py
proxy_messages_aiogram/storages/sqlite_storage.py
proxy_messages_aiogram/storages/types.py
proxy_messages_aiogram/texts.py
proxy_messages_aiogram/utils.py
proxy_messages_aiogram-0.1.7.dist-info/LICENSE
proxy_messages_aiogram-0.1.7.dist-info/METADATA
proxy_messages_aiogram-0.1.7.dist-info/WHEEL
proxy_messages_aiogram-0.1.7.dist-info/RECORD
