Metadata-Version: 2.1
Name: proxy-messages-aiogram
Version: 0.1.7
Summary: The easiest way to proxy messages from a bot to a selected chat-forum
Home-page: https://gitlab.com/rocshers/python/proxy-messages-aiogram
License: MIT
Author: Aleksei Marusich
Author-email: aleksei.marusich@rocshers.com
Requires-Python: >=3.12,<4
Classifier: Intended Audience :: Developers
Classifier: License :: OSI Approved :: MIT License
Classifier: Programming Language :: Python
Classifier: Programming Language :: Python :: 3
Classifier: Programming Language :: Python :: 3.12
Classifier: Programming Language :: Python :: 3 :: Only
Classifier: Topic :: Software Development :: Libraries
Classifier: Topic :: Software Development :: Libraries :: Python Modules
Classifier: Topic :: System :: Archiving :: Packaging
Classifier: Topic :: System :: Software Distribution
Requires-Dist: aiogram (>3)
Requires-Dist: pydantic (>2)
Requires-Dist: xxhash (>3)
Project-URL: Repository, https://gitlab.com/rocshers/python/proxy-messages-aiogram
